<!--
/*=========================================================
 *   )      (\_     | WOLFPACK 13.0.0 Scripts
 *  ((    _/{  "-;  | Created by: Dreoth
 *   )).-' {{ ;'`   | Revised by:
 *  ( (  ;._ \\     | Last modification:
 *=======================================================*/
-->
<definitions>

	<!-- Crescent Blade-->
	<item id="26cb">
		<id>0x26cb</id>
		<twohanded />
		<decay />
		<nodye />
		<sellprice>20</sellprice>
		<buyprice>41</buyprice>
		<durability><random min="30" max="75" /></durability>
		<weight>8.0</weight>
		<tag name="resname" value="iron" />
		<type>1001</type>
		<events>equipment,blades</events>
		<category>Weapons\Swords\Crescent Blade (N/S)</category>
	</item>

	<item id="26c1" inherit="26cb">
		<id>0x26c1</id>
		<baseid>26cb</baseid>
		<category>Weapons\Swords\Crescent Blade (E/W)</category>
	</item>

</definitions>
