
<definitions>

	<!-- Executioners Axe -->
	<item id="f45">
		<id>0x0f45</id>
		<twohanded />
		<decay />
		<nodye />
		<sellprice>16</sellprice>
		<buyprice>27</buyprice>
		<durability><random min="30" max="46" /></durability>
		<weight>3.0</weight>
		<tag name="req_str" value="40" type="int" />
		<tag name="resname" value="iron" />
		<tag name="remaining_uses" type="int" value="35" />
		<events>equipment,weapons.blades</events>
		<category>Weapons\Axes\Executioner's Axe (N/S)</category>
		<type>1002</type>
	</item>

	<item id="f46" inherit="f45">
		<id>0xf46</id>
		<category>Weapons\Axes\Executioner's Axe (E/W)</category>
	</item>

</definitions>
