<!--
/*=========================================================
 *   )      (\_     | WOLFPACK 13.0.0 Scripts
 *  ((    _/{  "-;  | Created by: Dreoth
 *   )).-' {{ ;'`   | Revised by:
 *  ( (  ;._ \\     | Last modification:
 *=======================================================*/
-->
<definitions>

	<!-- phoenix -->
	<npc id="phoenix" inherit="monster_base">
		<name>phoenix</name>
		<id>5</id>
		<skin>0x66d</skin>
		<karma>0</karma>
		<inherit id="FAME_L5" />
		<!-- Stats -->
		<str><random min="504" max="700"/></str>
		<dex><random min="202" max="300"/></dex>
		<int><random min="902" max="1000"/></int>
		<maxhitpoints><random min="340" max="383" /></maxhitpoints>
		<!-- Skills -->
		<evaluatingintel><random min="902" max="1000"/></evaluatingintel>
		<magery><random min="902" max="1000"/></magery>
		<meditation><random min="751" max="1000"/></meditation>
		<magicresistance><random min="860" max="1350"/></magicresistance>
		<tactics><random min="801" max="900"/></tactics>
		<wrestling><random min="901" max="1000"/></wrestling>
		<!-- Damage -->
		<mindamage>77</mindamage>
		<maxdamage>92</maxdamage>
		<tag name="dmg_fire" value="50" type="int" />
		<!-- Resists -->
		<tag name="dmg_energy" value="40,50" type="int" />
		<tag name="dmg_fire" value="60,70" type="int" />
		<tag name="dmg_physical" value="45,55" type="int" />
		<tag name="dmg_poison" value="25,35" type="int" />
		<!-- Misc. -->
		<desc>For aeons the phoenix has been a symbol of hope. Looking much like the majestic eagle, the phoenix has wings of flame. Those foolish enough to hope to kill a phoenix for the feathers will find the phoenix is noeasy target. Talons of the phoenix are harder than steel and can rend even plate armor. Few can best the phoenix in one-on-one battle.</desc>
		<!-- Missing: Accessory -->
		<lootpacks>lootpack_filthy_rich;lootpack_rich</lootpacks>
		<category>Monsters\Common\Phoenix</category>
		
		<!-- Carve -->
		<intproperty name="carve_feathers" value="36" />
		<intproperty name="carve_meat" value="1" />
		<strproperty name="carve_meat_type" value="bird" />
	</npc>

</definitions>
