<!--
/*=========================================================
 *   )      (\_     | WOLFPACK 13.0.0 Scripts
 *  ((    _/{  "-;  | Created by: Dreoth
 *   )).-' {{ ;'`   | Revised by:
 *  ( (  ;._ \\     | Last modification:
 *=======================================================*/
-->
<definitions>

	<!-- Dog -->
	<npc id="dog" inherit="animal_base">
		<name>dog</name>
		<id>217</id>
		<ai>Animal_Domestic</ai>
		<skin><random list="SKINS_ANIMAL" /></skin>
		<inherit id="KARMA_NL0" />
		<inherit id="FAME_L1" />
		<!-- Stats -->
		<str><random min="27" max="37" /></str>
		<dex><random min="28" max="43" /></dex>
		<int><random min="29" max="37" /></int>
		<!-- Status -->
		<maxhitpoints><random min="17" max="22" /></maxhitpoints>
		<maxmana>0</maxmana>
		<!-- Damage -->
		<mindamage>5</mindamage>
		<maxdamage>9</maxdamage>
		<!-- Defense -->
		<tag name="res_physical" value="10,15" type="int" />
		<!-- Skills -->
		<wrestling><random min="192" max="310" /></wrestling>
		<tactics><random min="192" max="310" /></tactics>
		<magicresistance><random min="221" max="470" /></magicresistance>
		<anatomy>0</anatomy>
		<!-- Misc. -->
		<controlslots>1</controlslots>
		<mintaming>0</mintaming>
		<food>0</food>
		<carve>carve_dog</carve>
		<bindmenu>tame_menu,pet_menu</bindmenu>
		<category>Animals\Canine\Dog</category>
	</npc>

</definitions>
